MANIFEST.in
README.md
setup.py
src/weirb/__init__.py
src/weirb/app.py
src/weirb/cli.py
src/weirb/client.py
src/weirb/config.py
src/weirb/context.py
src/weirb/error.py
src/weirb/helper.py
src/weirb/logger.py
src/weirb/request.py
src/weirb/response.py
src/weirb/router.py
src/weirb/scope.py
src/weirb/service.py
src/weirb/shell.py
src/weirb/tagger.py
src/weirb.egg-info/PKG-INFO
src/weirb.egg-info/SOURCES.txt
src/weirb.egg-info/dependency_links.txt
src/weirb.egg-info/entry_points.txt
src/weirb.egg-info/requires.txt
src/weirb.egg-info/top_level.txt
src/weirb/compat/__init__.py
src/weirb/compat/_contextlib.py
src/weirb/compat/contextlib.py
src/weirb/docs-template/Dockerfile
src/weirb/docs-template/_config.yml
src/weirb/docs-template/fabfile.py
src/weirb/docs-template/themes/simple2/base.html
src/weirb/docs-template/themes/simple2/index.html
src/weirb/docs-template/themes/simple2/page.html
src/weirb/docs-template/themes/simple2/static/css/style.css
src/weirb/docs-template/themes/simple2/static/css/tango.css
src/weirb/generator/__init__.py
src/weirb/generator/errors.md.mako
src/weirb/generator/generator.py
src/weirb/generator/intro.md.mako
src/weirb/generator/service.md.mako
src/weirb/project-template/echo/__init__.py
src/weirb/project-template/echo/config.py
src/weirb/project-template/echo/__pycache__/__init__.cpython-36.pyc
src/weirb/project-template/echo/__pycache__/config.cpython-36.pyc
src/weirb/project-template/echo/services/echo.py
src/weirb/project-template/echo/services/hello.py
src/weirb/project-template/echo/services/__pycache__/echo.cpython-36.pyc
src/weirb/project-template/echo/services/__pycache__/hello.cpython-36.pyc
src/weirb/server/__init__.py
src/weirb/server/parser.py
src/weirb/server/request.py
src/weirb/server/response.py
src/weirb/server/server.py
src/weirb/server/worker.py