Metadata-Version: 1.2
Name: weirb
Version: 0.5.1
Summary: Weird Web Framework
Home-page: https://github.com/guyskk/weirb
Author: guyskk
Author-email: guyskk@qq.com
License: UNKNOWN
Platform: UNKNOWN
Classifier: Development Status :: 3 - Alpha
Classifier: Intended Audience :: Developers
Classifier: Topic :: Software Development :: Build Tools
Classifier: License :: OSI Approved :: MIT License
Classifier: Programming Language :: Python :: 3.6
Requires-Python: >=3.6
